word2wiz/__init__.py
word2wiz/config.py
word2wiz/mark_parser.py
word2wiz/spell_helper.py
word2wiz/unwanted_matches.txt
word2wiz/util.py
word2wiz/version.py
word2wiz/word.py
word2wiz/word2wiz.py
word2wiz/spell/control.spl
word2wiz/spell/main.spl
word2wiz-0.3.1.dist-info/DESCRIPTION.rst
word2wiz-0.3.1.dist-info/METADATA
word2wiz-0.3.1.dist-info/RECORD
word2wiz-0.3.1.dist-info/WHEEL
word2wiz-0.3.1.dist-info/entry_points.txt
word2wiz-0.3.1.dist-info/metadata.json
word2wiz-0.3.1.dist-info/top_level.txt
