Metadata-Version: 2.0
Name: word2wiz
Version: 0.3.1
Summary: A tool to create wizard configurations from MS word documents
Home-page: http://github.com/joserc87/word2wiz
Author: Jose Ramon Cano
Author-email: jose.cano@theconsultancyfirm.com
License: MIT
Keywords: word2wiz document-wizard docwiz spell
Platform: UNKNOWN
Classifier: Development Status :: 3 - Alpha
Classifier: Intended Audience :: Developers
Classifier: Topic :: Utilities
Classifier: License :: OSI Approved :: MIT License
Classifier: Programming Language :: Python :: 3
Classifier: Programming Language :: Python :: 3.3
Classifier: Programming Language :: Python :: 3.4
Classifier: Programming Language :: Python :: 3.5
Requires-Dist: Flask
Requires-Dist: Jinja2
Requires-Dist: python-docx
Provides-Extra: test
Requires-Dist: behave; extra == 'test'
